LICENSE.txt
README.md
setup.cfg
setup.py
MidiCompose/__init__.py
MidiCompose/metronome.py
MidiCompose/objects.py
MidiCompose/playback.py
MidiCompose/scratch.py
MidiCompose/utilities.py
MidiCompose.egg-info/PKG-INFO
MidiCompose.egg-info/SOURCES.txt
MidiCompose.egg-info/dependency_links.txt
MidiCompose.egg-info/requires.txt
MidiCompose.egg-info/top_level.txt
MidiCompose/analysis/__init__.py
MidiCompose/analysis/midi_analysis.py
MidiCompose/logic/__init__.py
MidiCompose/logic/harmony/__init__.py
MidiCompose/logic/harmony/chord.py
MidiCompose/logic/harmony/chord_sequence.py
MidiCompose/logic/harmony/figure.py
MidiCompose/logic/harmony/interval.py
MidiCompose/logic/harmony/interval_mapping.py
MidiCompose/logic/harmony/key.py
MidiCompose/logic/harmony/note.py
MidiCompose/logic/harmony/note_mapping.py
MidiCompose/logic/melody/__init__.py
MidiCompose/logic/melody/melody.py
MidiCompose/logic/melody/note_set.py
MidiCompose/logic/melody/scale.py
MidiCompose/logic/rhythm/__init__.py
MidiCompose/logic/rhythm/beat.py
MidiCompose/logic/rhythm/measure.py
MidiCompose/logic/rhythm/part.py
MidiCompose/logic/rhythm/time_unit.py
MidiCompose/translation/__init__.py
MidiCompose/translation/midi_translation.py
MidiCompose/translation/state_translation.py
MidiCompose/translation/track_builder.py