Metadata-Version: 2.1
Name: MidiCompose
Version: 0.0.5
Summary: Library for programatically composing music using midi.
Home-page: https://github.com/aParthemer/MidiCompose
Author: Alex Parthemer
Author-email: alexparthemer@gmail.com
License: MIT
Download-URL: https://github.com/aParthemer/MidiCompose/archive/refs/tags/v_005.tar.gz
Keywords: midi,python,music
Platform: UNKNOWN
Classifier: Development Status :: 3 - Alpha
Classifier: Intended Audience :: Developers
Classifier: Topic :: Software Development :: Build Tools
Classifier: License :: OSI Approved :: MIT License
Classifier: Programming Language :: Python :: 3
Requires-Python: >=3.6
License-File: LICENSE.txt
